fdpy/__init__.py
fdpy/fdpy.py
fdpy/help_menu.py
fdpy/helper.py
fdpy-0.2.0.dist-info/LICENSE
fdpy-0.2.0.dist-info/WHEEL
fdpy-0.2.0.dist-info/METADATA
fdpy-0.2.0.dist-info/RECORD
