Metadata-Version: 2.1
Name: fdpy
Version: 0.2.0
Summary: fd wrapper for Python
License: MIT
Author: Alyetama
Author-email: 56323389+Alyetama@users.noreply.github.com
Requires-Python: >=3.6,<4.0
Classifier: License :: OSI Approved :: MIT License
Classifier: Programming Language :: Python :: 3
Classifier: Programming Language :: Python :: 3.10
Classifier: Programming Language :: Python :: 3.6
Classifier: Programming Language :: Python :: 3.7
Classifier: Programming Language :: Python :: 3.8
Classifier: Programming Language :: Python :: 3.9
